tree_sitter_tools/__init__.py
tree_sitter_tools/analysis/__init__.py
tree_sitter_tools/analysis/walker.py
tree_sitter_tools/indexer/__init__.py
tree_sitter_tools/indexer/__main__.py
tree_sitter_tools/indexer/scan.py
tree_sitter_tools/indexer/symbol_indexer.py
tree_sitter_tools/parser/__init__.py
tree_sitter_tools/parser/base.py
tree_sitter_tools/parser/parser.py
tree_sitter_tools/parser/visitor.py
tree_sitter_tools/parser/walker.py
tree_sitter_tools/searcher/__init__.py
tree_sitter_tools/searcher/searcher.py
tree_sitter_tools/utils/__init__.py
tree_sitter_tools/utils/base.py
tree_sitter_tools/utils/printer.py
tree_sitter_tools-0.1.5.dist-info/METADATA
tree_sitter_tools-0.1.5.dist-info/WHEEL
tree_sitter_tools-0.1.5.dist-info/RECORD
