Metadata-Version: 2.1
Name: tree-sitter-tools
Version: 0.1.5
Summary: 
Author: SiyuChen
Author-email: ryougi201@gmail.com
Requires-Python: >=3.9,<4.0
Classifier: Programming Language :: Python :: 3
Classifier: Programming Language :: Python :: 3.9
Classifier: Programming Language :: Python :: 3.10
Classifier: Programming Language :: Python :: 3.11
Classifier: Programming Language :: Python :: 3.12
Requires-Dist: pyarrow (>=17.0.0,<18.0.0)
Requires-Dist: pydantic (>=2.8.2,<3.0.0)
Requires-Dist: tree-sitter (>=0.22.3,<0.23.0)
